pyweb/__init__.py
pyweb/__init__.pyc
pyweb/app.py
pyweb/__pycache__/__init__.cpython-37.pyc
pyweb/blueprints/__init__.py
pyweb/blueprints/admin/__init__.py
pyweb/blueprints/admin/api.py
pyweb/blueprints/admin/templates/404.html
pyweb/blueprints/admin/templates/base.html
pyweb/blueprints/admin/templates/bootstrap.html
pyweb/blueprints/admin/templates/index.html
pyweb/blueprints/post/__init__.py
pyweb/blueprints/post/api.py
pyweb/blueprints/post/static/performance.js
pyweb/blueprints/whoosh/__init__.py
pyweb/blueprints/whoosh/api.py
pyweb/blueprints/whoosh/whoosh.py
pyweb/blueprints/whoosh/static/whoosh.js
pyweb/blueprints/whoosh/templates/results.html
pyweb/exts/__init__.py
pyweb/exts/exts.py
pyweb/pydash/__init__.py
pyweb/pydash/common.py
pyweb/pydash/pydash/__init__.py
pyweb/pydash/pydash/callbacks.py
pyweb/pydash/pydash/dash_util.py
pyweb/testing/__init__.py
pyweb/testing/response.py
pyweb/web/__init__.py
pyweb/web/application.py
pyweb/web/extension.py
pyweb/web/highcharts.py
pyweb/web/parser.py
pyweb/web/requests.py
lob_pyweb-0.6.2.dist-info/LICENSE.txt
lob_pyweb-0.6.2.dist-info/METADATA
lob_pyweb-0.6.2.dist-info/WHEEL
lob_pyweb-0.6.2.dist-info/top_level.txt
lob_pyweb-0.6.2.dist-info/RECORD
