Metadata-Version: 2.1
Name: lob-pyweb
Version: 0.6.2
Summary: UNKNOWN
Home-page: https://github.com/lobnek/pyweb
Author: Thomas Schmelzer
Author-email: thomas.schmelzer@gmail.com
License: MIT
Platform: UNKNOWN
Requires-Dist: flask (>=1.1.2)
Requires-Dist: flask-caching (>=1.9.0)
Requires-Dist: waitress (>=1.4.4)
Requires-Dist: dash (>=1.12.0)
Requires-Dist: dash-daq (>=0.5.0)
Requires-Dist: flask-mongoengine (>=0.9.5)
Requires-Dist: whitenoise (>=5.1.0)
Requires-Dist: dnspython (>=1.16.0)
Requires-Dist: flask-bootstrap (>=3.3.7.1)
